async_fifo.v
`timescale 1ns/1ps

module async_fifo #(
    parameter DATA_WIDTH = 8,
    parameter DEPTH      = 16,
    parameter ADDR_WIDTH = 4
)(
    input                       wr_clk,
    input                       wr_rst,
    input                       wr_en,
    input  [DATA_WIDTH-1:0]     wr_data,
    output                      full,

    input                       rd_clk,
    input                       rd_rst,
    input                       rd_en,
    output reg [DATA_WIDTH-1:0] rd_data,
    output                      empty
);

    // -------------------------------------------------------------------------
    // Memory
    // -------------------------------------------------------------------------
    reg [DATA_WIDTH-1:0] mem [0:DEPTH-1];

    // -------------------------------------------------------------------------
    // Pointers (ADDR_WIDTH+1 bits - MSB used for full/empty distinction)
    // -------------------------------------------------------------------------
    reg  [ADDR_WIDTH:0] wr_bin,  wr_gray;
    reg  [ADDR_WIDTH:0] rd_bin,  rd_gray;

    // Next-state: simple unconditional +1  (NO feedback from full/empty)
    wire [ADDR_WIDTH:0] wr_bin_next  = wr_bin + 1'b1;
    wire [ADDR_WIDTH:0] wr_gray_next = (wr_bin_next >> 1) ^ wr_bin_next;

    wire [ADDR_WIDTH:0] rd_bin_next  = rd_bin + 1'b1;
    wire [ADDR_WIDTH:0] rd_gray_next = (rd_bin_next >> 1) ^ rd_bin_next;

    // -------------------------------------------------------------------------
    // Synchronizers
    // -------------------------------------------------------------------------
    reg [ADDR_WIDTH:0] rd_gray_sync1, rd_gray_sync2;   // rd_gray  ? wr_clk domain
    reg [ADDR_WIDTH:0] wr_gray_sync1, wr_gray_sync2;   // wr_gray  ? rd_clk domain

    // -------------------------------------------------------------------------
    // EMPTY flag  (read-clock domain)
    //   Compare CURRENT rd_gray with the synchronised wr_gray.
    //   Using the current pointer (not _next) avoids asserting empty one beat early.
    // -------------------------------------------------------------------------
    assign empty = (rd_gray == wr_gray_sync2);

    // -------------------------------------------------------------------------
    // FULL flag  (write-clock domain)
    //   The FIFO is full when the next write pointer equals the synchronised
    //   read pointer with the two MSBs inverted (standard Gray-code full check).
    // -------------------------------------------------------------------------
    wire [ADDR_WIDTH:0] rd_gray_full_cmp =
        { ~rd_gray_sync2[ADDR_WIDTH:ADDR_WIDTH-1],
           rd_gray_sync2[ADDR_WIDTH-2:0] };

    assign full = (wr_gray_next == rd_gray_full_cmp);

    // -------------------------------------------------------------------------
    // Write pointer registers  (wr_clk domain)
    //   The enable guard lives HERE - not inside the combinational next-pointer.
    // -------------------------------------------------------------------------
    always @(posedge wr_clk) begin
        if (wr_rst) begin
            wr_bin  <= {(ADDR_WIDTH+1){1'b0}};
            wr_gray <= {(ADDR_WIDTH+1){1'b0}};
        end else if (wr_en && !full) begin
            wr_bin  <= wr_bin_next;
            wr_gray <= wr_gray_next;
        end
    end

    // -------------------------------------------------------------------------
    // Read pointer registers  (rd_clk domain)
    // -------------------------------------------------------------------------
    always @(posedge rd_clk) begin
        if (rd_rst) begin
            rd_bin  <= {(ADDR_WIDTH+1){1'b0}};
            rd_gray <= {(ADDR_WIDTH+1){1'b0}};
        end else if (rd_en && !empty) begin
            rd_bin  <= rd_bin_next;
            rd_gray <= rd_gray_next;
        end
    end

    // -------------------------------------------------------------------------
    // Synchronise rd_gray into wr_clk domain  (2-FF synchroniser)
    // -------------------------------------------------------------------------
    always @(posedge wr_clk) begin
        if (wr_rst) begin
            rd_gray_sync1 <= {(ADDR_WIDTH+1){1'b0}};
            rd_gray_sync2 <= {(ADDR_WIDTH+1){1'b0}};
        end else begin
            rd_gray_sync1 <= rd_gray;
            rd_gray_sync2 <= rd_gray_sync1;
        end
    end

    // -------------------------------------------------------------------------
    // Synchronise wr_gray into rd_clk domain  (2-FF synchroniser)
    // -------------------------------------------------------------------------
    always @(posedge rd_clk) begin
        if (rd_rst) begin
            wr_gray_sync1 <= {(ADDR_WIDTH+1){1'b0}};
            wr_gray_sync2 <= {(ADDR_WIDTH+1){1'b0}};
        end else begin
            wr_gray_sync1 <= wr_gray;
            wr_gray_sync2 <= wr_gray_sync1;
        end
    end

    // -------------------------------------------------------------------------
    // Memory write  (wr_clk domain)
    // -------------------------------------------------------------------------
    always @(posedge wr_clk) begin
        if (wr_en && !full)
            mem[wr_bin[ADDR_WIDTH-1:0]] <= wr_data;
    end

    // -------------------------------------------------------------------------
    // Memory read - registered output  (rd_clk domain)
    // -------------------------------------------------------------------------
    always @(posedge rd_clk) begin
        if (rd_rst)
            rd_data <= {DATA_WIDTH{1'b0}};
        else if (rd_en && !empty)
            rd_data <= mem[rd_bin[ADDR_WIDTH-1:0]];
    end

endmodule

tb_async_fifo.v
`timescale 1ns/1ps

module async_fifo_tb;

    // -------------------------------------------------------------------------
    // Parameters
    // -------------------------------------------------------------------------
    parameter DATA_WIDTH = 8;
    parameter DEPTH      = 16;
    parameter ADDR_WIDTH = 4;

    parameter WR_CLK_PERIOD = 10;  // 100 MHz write clock
    parameter RD_CLK_PERIOD = 17;  // ~59 MHz read clock (intentionally different)

    // -------------------------------------------------------------------------
    // DUT Ports
    // -------------------------------------------------------------------------
    reg                   wr_clk, wr_rst, wr_en;
    reg  [DATA_WIDTH-1:0] wr_data;
    wire                  full;

    reg                   rd_clk, rd_rst, rd_en;
    wire [DATA_WIDTH-1:0] rd_data;
    wire                  empty;

    // -------------------------------------------------------------------------
    // Instantiate DUT
    // -------------------------------------------------------------------------
    async_fifo #(
        .DATA_WIDTH(DATA_WIDTH),
        .DEPTH     (DEPTH),
        .ADDR_WIDTH(ADDR_WIDTH)
    ) dut (
        .wr_clk  (wr_clk),
        .wr_rst  (wr_rst),
        .wr_en   (wr_en),
        .wr_data (wr_data),
        .full    (full),
        .rd_clk  (rd_clk),
        .rd_rst  (rd_rst),
        .rd_en   (rd_en),
        .rd_data (rd_data),
        .empty   (empty)
    );

    // -------------------------------------------------------------------------
    // Clock Generation
    // -------------------------------------------------------------------------
    initial wr_clk = 0;
    always #(WR_CLK_PERIOD/2) wr_clk = ~wr_clk;

    initial rd_clk = 0;
    always #(RD_CLK_PERIOD/2) rd_clk = ~rd_clk;

    // -------------------------------------------------------------------------
    // Scoreboard / Tracking
    // -------------------------------------------------------------------------
    integer errors     = 0;
    integer wr_count   = 0;
    integer rd_count   = 0;

    // Reference queue (simple shift-register model, max DEPTH entries)
    reg [DATA_WIDTH-1:0] ref_queue [0:DEPTH-1];
    integer              ref_head  = 0;   // next read index
    integer              ref_tail  = 0;   // next write index
    integer              ref_count = 0;   // items in queue

    // -------------------------------------------------------------------------
    // Task: Apply Reset (both domains)
    // -------------------------------------------------------------------------
    task apply_reset;
        begin
            wr_rst = 1; rd_rst = 1;
            wr_en  = 0; rd_en  = 0;
            wr_data = 0;
            repeat(4) @(posedge wr_clk);
            repeat(4) @(posedge rd_clk);
            @(posedge wr_clk); wr_rst = 0;
            @(posedge rd_clk); rd_rst = 0;
            $display("[%0t] Reset de-asserted.", $time);
        end
    endtask

    // -------------------------------------------------------------------------
    // Task: Write one word (write-clock domain)
    // -------------------------------------------------------------------------
    task write_word;
        input [DATA_WIDTH-1:0] data;
        begin
            @(posedge wr_clk);
            if (!full) begin
                wr_en   = 1;
                wr_data = data;
                // Push to reference model
                ref_queue[ref_tail] = data;
                ref_tail  = (ref_tail + 1) % DEPTH;
                ref_count = ref_count + 1;
                wr_count  = wr_count  + 1;
                @(posedge wr_clk);
                wr_en = 0;
            end else begin
                $display("[%0t] WARN: write_word called but FIFO is full - skipping.", $time);
            end
        end
    endtask

    // -------------------------------------------------------------------------
    // Task: Read one word and check against reference model (read-clock domain)
    // -------------------------------------------------------------------------
    task read_and_check;
        reg [DATA_WIDTH-1:0] expected;
        begin
            @(posedge rd_clk);
            if (!empty) begin
                rd_en = 1;
                @(posedge rd_clk);   // data registered on this edge
                rd_en = 0;
                #1;                  // tiny settle time

                expected  = ref_queue[ref_head];
                ref_head  = (ref_head + 1) % DEPTH;
                ref_count = ref_count - 1;
                rd_count  = rd_count  + 1;

                if (rd_data !== expected) begin
                    $display("[%0t] MISMATCH: rd_data=0x%0h  expected=0x%0h",
                             $time, rd_data, expected);
                    errors = errors + 1;
                end else begin
                    $display("[%0t] OK  read 0x%0h", $time, rd_data);
                end
            end else begin
                $display("[%0t] WARN: read_and_check called but FIFO is empty - skipping.", $time);
            end
        end
    endtask

    // -------------------------------------------------------------------------
    // Test sequence
    // -------------------------------------------------------------------------
    integer i;

    initial begin
        $dumpfile("async_fifo_tb.vcd");
        $dumpvars(0, async_fifo_tb);

        // ---- 0. Initialise -----------------------------------------------
        wr_clk = 0; rd_clk = 0;
        wr_rst = 1; rd_rst = 1;
        wr_en  = 0; rd_en  = 0;
        wr_data = 0;

        // ---- 1. Reset -------------------------------------------------------
        $display("\n=== TEST 1: Reset behaviour ===");
        apply_reset;
        if (!empty)
            begin $display("FAIL: empty should be 1 after reset"); errors=errors+1; end
        else
            $display("PASS: empty asserted after reset");
        if (full)
            begin $display("FAIL: full should be 0 after reset"); errors=errors+1; end
        else
            $display("PASS: full de-asserted after reset");

        // ---- 2. Basic Write then Read ---------------------------------------
        $display("\n=== TEST 2: Basic write-then-read ===");
        write_word(8'hA5);
        write_word(8'h3C);
        write_word(8'h7F);
        // Allow Gray-code sync to propagate (2 rd_clk cycles)
        repeat(4) @(posedge rd_clk);
        read_and_check;
        read_and_check;
        read_and_check;
        repeat(4) @(posedge rd_clk);
        if (!empty)
            begin $display("FAIL: FIFO should be empty after draining"); errors=errors+1; end
        else
            $display("PASS: FIFO empty after draining");

        // ---- 3. Fill to full ------------------------------------------------
        $display("\n=== TEST 3: Fill FIFO to full ===");
        for (i = 0; i < DEPTH; i = i + 1)
            write_word(i[DATA_WIDTH-1:0]);
        // Allow sync to propagate
        repeat(4) @(posedge wr_clk);
        if (!full)
            begin $display("FAIL: FIFO should be full"); errors=errors+1; end
        else
            $display("PASS: full asserted after %0d writes", DEPTH);

        // ---- 4. Write while full (should be dropped) -----------------------
        $display("\n=== TEST 4: Write while full ===");
        @(posedge wr_clk);
        wr_en   = 1;
        wr_data = 8'hFF;
        @(posedge wr_clk);
        wr_en = 0;
        $display("Write-while-full attempted (should be silently discarded by DUT).");

        // ---- 5. Drain the FIFO --------------------------------------------
        $display("\n=== TEST 5: Drain full FIFO ===");
        repeat(4) @(posedge rd_clk);
        for (i = 0; i < DEPTH; i = i + 1)
            read_and_check;
        repeat(6) @(posedge rd_clk);
        if (!empty)
            begin $display("FAIL: FIFO should be empty after full drain"); errors=errors+1; end
        else
            $display("PASS: FIFO empty after full drain");

        // ---- 6. Read while empty ------------------------------------------
        $display("\n=== TEST 6: Read while empty ===");
        @(posedge rd_clk);
        rd_en = 1;
        @(posedge rd_clk);
        rd_en = 0;
        $display("Read-while-empty attempted (rd_data should hold previous value).");

        // ---- 7. Simultaneous Write and Read (streaming) -------------------
        $display("\n=== TEST 7: Concurrent write & read (streaming) ===");
        fork
            begin : write_stream
                for (i = 0; i < 32; i = i + 1) begin
                    @(posedge wr_clk);
                    if (!full) begin
                        wr_en   = 1;
                        wr_data = (8'h10 + i[DATA_WIDTH-1:0]);
                        ref_queue[ref_tail] = wr_data;
                        ref_tail  = (ref_tail + 1) % DEPTH;
                        ref_count = ref_count + 1;
                        wr_count  = wr_count  + 1;
                        @(posedge wr_clk);
                        wr_en = 0;
                    end
                end
            end
            begin : read_stream
                // Let a few writes complete first so FIFO isn't empty
                repeat(8) @(posedge rd_clk);
                for (i = 0; i < 32; i = i + 1) begin
                    repeat(2) @(posedge rd_clk);
                    if (!empty) begin
                        rd_en = 1;
                        @(posedge rd_clk);
                        rd_en = 0;
                        #1;
                        if (ref_count > 0) begin
                            if (rd_data !== ref_queue[ref_head]) begin
                                $display("[%0t] MISMATCH (stream): rd_data=0x%0h expected=0x%0h",
                                         $time, rd_data, ref_queue[ref_head]);
                                errors = errors + 1;
                            end else begin
                                $display("[%0t] OK  stream read 0x%0h", $time, rd_data);
                            end
                            ref_head  = (ref_head + 1) % DEPTH;
                            ref_count = ref_count - 1;
                            rd_count  = rd_count  + 1;
                        end
                    end
                end
            end
        join

        // Drain any leftovers
        repeat(6) @(posedge rd_clk);
        while (!empty) begin
            read_and_check;
            repeat(2) @(posedge rd_clk);
        end

        // ---- 8. Pointer wrap-around (write > DEPTH times total) -----------
        $display("\n=== TEST 8: Pointer wrap-around ===");
        for (i = 0; i < DEPTH; i = i + 1)
            write_word((8'hC0 + i[DATA_WIDTH-1:0]));
        repeat(4) @(posedge rd_clk);
        for (i = 0; i < DEPTH; i = i + 1)
            read_and_check;
        repeat(4) @(posedge rd_clk);
        if (!empty)
            begin $display("FAIL: FIFO should be empty after wrap-around drain"); errors=errors+1; end
        else
            $display("PASS: Wrap-around drain OK");

        // ---- 9. Summary ----------------------------------------------------
        $display("\n========================================");
        $display("  Total writes : %0d", wr_count);
        $display("  Total reads  : %0d", rd_count);
        $display("  Errors       : %0d", errors);
        if (errors == 0)
            $display("  *** ALL TESTS PASSED ***");
        else
            $display("  *** %0d TEST(S) FAILED ***", errors);
        $display("========================================\n");

        $finish;
    end

    // -------------------------------------------------------------------------
    // Timeout watchdog
    // -------------------------------------------------------------------------
    initial begin
        #500000;
        $display("TIMEOUT: simulation exceeded 500 us");
        $finish;
    end

endmodule

Asynchronous-fifo/Asynchronous-fifo.sim/sim_1/behav/xsim/async_fifo_tb.vcd
$date
   Tue Mar  3 13:48:45 2026
$end

$version
  2023.2
  $dumpfile ("async_fifo_tb.vcd") 
$end

$timescale
  1ps
$end

$scope module async_fifo_tb $end
$var reg 1 ! wr_clk $end
$var reg 1 " wr_rst $end
$var reg 1 # wr_en $end
$var reg 8 $ wr_data [7:0] $end
$var wire 1 % full $end
$var reg 1 & rd_clk $end
$var reg 1 ' rd_rst $end
$var reg 1 ( rd_en $end
$var wire 8 ) rd_data [7:0] $end
$var wire 1 * empty $end
$var integer 32 + errors [31:0] $end
$var integer 32 , wr_count [31:0] $end
$var integer 32 - rd_count [31:0] $end
$var integer 32 . ref_head [31:0] $end
$var integer 32 / ref_tail [31:0] $end
$var integer 32 0 ref_count [31:0] $end
$var integer 32 1 i [31:0] $end
$scope module dut $end
$var wire 1 2 wr_clk $end
$var wire 1 3 wr_rst $end
$var wire 1 4 wr_en $end
$var wire 8 5 wr_data [7:0] $end
$var wire 1 % full $end
$var wire 1 6 rd_clk $end
$var wire 1 7 rd_rst $end
$var wire 1 8 rd_en $end
$var reg 8 9 rd_data [7:0] $end
$var wire 1 * empty $end
$var reg 5 : wr_bin [4:0] $end
$var reg 5 ; wr_gray [4:0] $end
$var reg 5 < rd_bin [4:0] $end
$var reg 5 = rd_gray [4:0] $end
$var wire 5 > wr_bin_next [4:0] $end
$var wire 5 ? wr_gray_next [4:0] $end
$var wire 5 @ rd_bin_next [4:0] $end
$var wire 5 A rd_gray_next [4:0] $end
$var reg 5 B rd_gray_sync1 [4:0] $end
$var reg 5 C rd_gray_sync2 [4:0] $end
$var reg 5 D wr_gray_sync1 [4:0] $end
$var reg 5 E wr_gray_sync2 [4:0] $end
$var wire 5 F rd_gray_full_cmp [4:0] $end
$upscope $end
$scope task apply_reset $end
$upscope $end
$scope task write_word $end
$var reg 8 G data [7:0] $end
$upscope $end
$scope task read_and_check $end
$var reg 8 H expected [7:0] $end
$upscope $end
$upscope $end
$enddefinitions $end

#0
$dumpvars
0!
1"
0#
b0 $
x%
0&
1'
0(
bx )
x*
b0 +
b0 ,
b0 -
b0 .
b0 /
b0 0
bx 1
02
13
04
b0 5
06
17
08
bx 9
bx :
bx ;
bx <
bx =
bx >
bx ?
bx @
bx A
bx B
bx C
bx D
bx E
bx F
bx G
bx H
$end

#5000
1!
0%
12
b0 :
b0 ;
b1 >
b1 ?
b0 B
b0 C
b11000 F

#8000
1&
b0 )
1*
16
b0 9
b0 <
b0 =
b1 @
b1 A
b0 D
b0 E

#10000
0!
02

#15000
1!
12

#16000
0&
06

#20000
0!
02

#24000
1&
16

#25000
1!
12

#30000
0!
02

#32000
0&
06

#35000
1!
12

#40000
0!
1&
02
16

#45000
1!
12

#48000
0&
06

#50000
0!
02

#55000
1!
12

#56000
1&
16

#60000
0!
02

#64000
0&
06

#65000
1!
12

#70000
0!
02

#72000
1&
16

#75000
1!
12

#80000
0!
0&
02
06

#85000
1!
12

#88000
1&
16

#90000
0!
02

#95000
1!
0"
12
03

#96000
0&
06

#100000
0!
02

#104000
1&
0'
16
07
b10100101 G

#105000
1!
1#
b10100101 $
b1 ,
b1 /
b1 0
12
14
b10100101 5
b1 :
b1 ;
b10 >
b11 ?

#110000
0!
02

#112000
0&
06

#115000
1!
0#
12
04
b111100 G

#120000
0!
1&
02
16
b1 D

#125000
1!
1#
b111100 $
b10 ,
b10 /
b10 0
12
14
b111100 5
b10 :
b11 ;
b11 >
b10 ?

#128000
0&
06

#130000
0!
02

#135000
1!
0#
12
04
b1111111 G

#136000
1&
0*
16
b11 D
b1 E

#140000
0!
02

#144000
0&
06

#145000
1!
1#
b1111111 $
b11 ,
b11 /
b11 0
12
14
b1111111 5
b11 :
b10 ;
b100 >
b110 ?

#150000
0!
02

#152000
1&
16
b10 D
b11 E

#155000
1!
0#
12
04

#160000
0!
0&
02
06

#165000
1!
12

#168000
1&
16
b10 E

#170000
0!
02

#175000
1!
12

#176000
0&
06

#180000
0!
02

#184000
1&
16

#185000
1!
12

#190000
0!
02

#192000
0&
06

#195000
1!
12

#200000
0!
1&
02
16

#205000
1!
12

#208000
0&
06

#210000
0!
02

#215000
1!
12

#216000
1&
16

#220000
0!
02

#224000
0&
06

#225000
1!
12

#230000
0!
02

#232000
1&
1(
b10100101 )
16
18
b10100101 9
b1 <
b1 =
b10 @
b11 A

#235000
1!
12
b1 B

#240000
0!
0&
02
06

#245000
1!
12
b1 C
b11001 F

#248000
1&
0(
16
08

#249000
b1 -
b1 .
b10 0
b10100101 H

#250000
0!
02

#255000
1!
12

#256000
0&
06

#260000
0!
02

#264000
1&
1(
b111100 )
16
18
b111100 9
b10 <
b11 =
b11 @
b10 A

#265000
1!
12
b11 B

#270000
0!
02

#272000
0&
06

#275000
1!
12
b11 C
b11011 F

#280000
0!
1&
0(
02
16
08

#281000
b10 -
b10 .
b1 0
b111100 H

#285000
1!
12

#288000
0&
06

#290000
0!
02

#295000
1!
12

#296000
1&
1(
b1111111 )
1*
16
18
b1111111 9
b11 <
b10 =
b100 @
b110 A

#300000
0!
02

#304000
0&
06

#305000
1!
12
b10 B

#310000
0!
02

#312000
1&
0(
16
08

#313000
b11 -
b11 .
b0 0
b1111111 H

#315000
1!
12
b10 C
b11010 F

#320000
0!
0&
02
06

#325000
1!
12

#328000
1&
16

#330000
0!
02

#335000
1!
12

#336000
0&
06

#340000
0!
02

#344000
1&
16

#345000
1!
12

#350000
0!
02

#352000
0&
06

#355000
1!
12

#360000
0!
1&
02
16

#365000
1!
12

#368000
0&
06

#370000
0!
02

#375000
1!
12

#376000
1&
b0 1
16
b0 G

#380000
0!
02

#384000
0&
06

#385000
1!
1#
b0 $
b100 ,
b100 /
b1 0
12
14
b0 5
b100 :
b110 ;
b101 >
b111 ?

#390000
0!
02

#392000
1&
16
b110 D

#395000
1!
0#
b1 1
12
04
b1 G

#400000
0!
0&
02
06

#405000
1!
1#
b1 $
b101 ,
b101 /
b10 0
12
14
b1 5
b101 :
b111 ;
b110 >
b101 ?

#408000
1&
0*
16
b111 D
b110 E

#410000
0!
02

#415000
1!
0#
b10 1
12
04
b10 G

#416000
0&
06

#420000
0!
02

#424000
1&
16
b111 E

#425000
1!
1#
b10 $
b110 ,
b110 /
b11 0
12
14
b10 5
b110 :
b101 ;
b111 >
b100 ?

#430000
0!
02

#432000
0&
06

#435000
1!
0#
b11 1
12
04
b11 G

#440000
0!
1&
02
16
b101 D

#445000
1!
1#
b11 $
b111 ,
b111 /
b100 0
12
14
b11 5
b111 :
b100 ;
b1000 >
b1100 ?

#448000
0&
06

#450000
0!
02

#455000
1!
0#
b100 1
12
04
b100 G

#456000
1&
16
b100 D
b101 E

#460000
0!
02

#464000
0&
06

#465000
1!
1#
b100 $
b1000 ,
b1000 /
b101 0
12
14
b100 5
b1000 :
b1100 ;
b1001 >
b1101 ?

#470000
0!
02

#472000
1&
16
b1100 D
b100 E

#475000
1!
0#
b101 1
12
04
b101 G

#480000
0!
0&
02
06

#485000
1!
1#
b101 $
b1001 ,
b1001 /
b110 0
12
14
b101 5
b1001 :
b1101 ;
b1010 >
b1111 ?

#488000
1&
16
b1101 D
b1100 E

#490000
0!
02

#495000
1!
0#
b110 1
12
04
b110 G

#496000
0&
06

#500000
0!
02

#504000
1&
16
b1101 E

#505000
1!
1#
b110 $
b1010 ,
b1010 /
b111 0
12
14
b110 5
b1010 :
b1111 ;
b1011 >
b1110 ?

#510000
0!
02

#512000
0&
06

#515000
1!
0#
b111 1
12
04
b111 G

#520000
0!
1&
02
16
b1111 D

#525000
1!
1#
b111 $
b1011 ,
b1011 /
b1000 0
12
14
b111 5
b1011 :
b1110 ;
b1100 >
b1010 ?

#528000
0&
06

#530000
0!
02

#535000
1!
0#
b1000 1
12
04
b1000 G

#536000
1&
16
b1110 D
b1111 E

#540000
0!
02

#544000
0&
06

#545000
1!
1#
b1000 $
b1100 ,
b1100 /
b1001 0
12
14
b1000 5
b1100 :
b1010 ;
b1101 >
b1011 ?

#550000
0!
02

#552000
1&
16
b1010 D
b1110 E

#555000
1!
0#
b1001 1
12
04
b1001 G

#560000
0!
0&
02
06

#565000
1!
1#
b1001 $
b1101 ,
b1101 /
b1010 0
12
14
b1001 5
b1101 :
b1011 ;
b1110 >
b1001 ?

#568000
1&
16
b1011 D
b1010 E

#570000
0!
02

#575000
1!
0#
b1010 1
12
04
b1010 G

#576000
0&
06

#580000
0!
02

#584000
1&
16
b1011 E

#585000
1!
1#
b1010 $
b1110 ,
b1110 /
b1011 0
12
14
b1010 5
b1110 :
b1001 ;
b1111 >
b1000 ?

#590000
0!
02

#592000
0&
06

#595000
1!
0#
b1011 1
12
04
b1011 G

#600000
0!
1&
02
16
b1001 D

#605000
1!
1#
b1011 $
b1111 ,
b1111 /
b1100 0
12
14
b1011 5
b1111 :
b1000 ;
b10000 >
b11000 ?

#608000
0&
06

#610000
0!
02

#615000
1!
0#
b1100 1
12
04
b1100 G

#616000
1&
16
b1000 D
b1001 E

#620000
0!
02

#624000
0&
06

#625000
1!
1#
b1100 $
b10000 ,
b0 /
b1101 0
12
14
b1100 5
b10000 :
b11000 ;
b10001 >
b11001 ?

#630000
0!
02

#632000
1&
16
b11000 D
b1000 E

#635000
1!
0#
b1101 1
12
04
b1101 G

#640000
0!
0&
02
06

#645000
1!
1#
b1101 $
b10001 ,
b1 /
b1110 0
12
14
b1101 5
b10001 :
b11001 ;
b10010 >
b11011 ?

#648000
1&
16
b11001 D
b11000 E

#650000
0!
02

#655000
1!
0#
b1110 1
12
04
b1110 G

#656000
0&
06

#660000
0!
02

#664000
1&
16
b11001 E

#665000
1!
1#
b1110 $
1%
b10010 ,
b10 /
b1111 0
12
14
b1110 5
b10010 :
b11011 ;
b10011 >
b11010 ?

#670000
0!
02

#672000
0&
06

#675000
1!
0#
b1111 1
12
04
b1111 G

#680000
0!
1&
02
16
b11011 D

#685000
1!
b10000 1
12

#688000
0&
06

#690000
0!
02

#695000
1!
12

#696000
1&
16
b11011 E

#700000
0!
02

#704000
0&
06

#705000
1!
12

#710000
0!
02

#712000
1&
16

#715000
1!
12

#720000
0!
0&
02
06

#725000
1!
12

#728000
1&
16

#730000
0!
02

#735000
1!
1#
b11111111 $
12
14
b11111111 5

#736000
0&
06

#740000
0!
02

#744000
1&
16

#745000
1!
0#
12
04

#750000
0!
02

#752000
0&
06

#755000
1!
12

#760000
0!
1&
02
16

#765000
1!
12

#768000
0&
06

#770000
0!
02

#775000
1!
12

#776000
1&
16

#780000
0!
02

#784000
0&
06

#785000
1!
12

#790000
0!
02

#792000
1&
16

#795000
1!
12

#800000
0!
0&
02
06

#805000
1!
12

#808000
1&
b0 1
16

#810000
0!
02

#815000
1!
12

#816000
0&
06

#820000
0!
02

#824000
1&
1(
b0 )
16
18
b0 9
b100 <
b110 =
b101 @
b111 A

#825000
1!
12
b110 B

#830000
0!
02

#832000
0&
06

#835000
1!
0%
12
b110 C
b11110 F

#840000
0!
1&
0(
02
16
08

#841000
b100 -
b100 .
b1110 0
b1 1
b0 H

#845000
1!
12

#848000
0&
06

#850000
0!
02

#855000
1!
12

#856000
1&
1(
b1 )
16
18
b1 9
b101 <
b111 =
b110 @
b101 A

#860000
0!
02

#864000
0&
06

#865000
1!
12
b111 B

#870000
0!
02

#872000
1&
0(
16
08

#873000
b101 -
b101 .
b1101 0
b10 1
b1 H

#875000
1!
12
b111 C
b11111 F

#880000
0!
0&
02
06

#885000
1!
12

#888000
1&
1(
b10 )
16
18
b10 9
b110 <
b101 =
b111 @
b100 A

#890000
0!
02

#895000
1!
12
b101 B

#896000
0&
06

#900000
0!
02

#904000
1&
0(
16
08

#905000
1!
b110 -
b110 .
b1100 0
b11 1
12
b101 C
b11101 F
b10 H

#910000
0!
02

#912000
0&
06

#915000
1!
12

#920000
0!
1&
1(
b11 )
02
16
18
b11 9
b111 <
b100 =
b1000 @
b1100 A

#925000
1!
12
b100 B

#928000
0&
06

#930000
0!
02

#935000
1!
12
b100 C
b11100 F

#936000
1&
0(
16
08

#937000
b111 -
b111 .
b1011 0
b100 1
b11 H

#940000
0!
02

#944000
0&
06

#945000
1!
12

#950000
0!
02

#952000
1&
1(
b100 )
16
18
b100 9
b1000 <
b1100 =
b1001 @
b1101 A

#955000
1!
12
b1100 B

#960000
0!
0&
02
06

#965000
1!
12
b1100 C
b10100 F

#968000
1&
0(
16
08

#969000
b1000 -
b1000 .
b1010 0
b101 1
b100 H

#970000
0!
02

#975000
1!
12

#976000
0&
06

#980000
0!
02

#984000
1&
1(
b101 )
16
18
b101 9
b1001 <
b1101 =
b1010 @
b1111 A

#985000
1!
12
b1101 B

#990000
0!
02

#992000
0&
06

#995000
1!
12
b1101 C
b10101 F

#1000000
0!
1&
0(
02
16
08

#1001000
b1001 -
b1001 .
b1001 0
b110 1
b101 H

#1005000
1!
12

#1008000
0&
06

#1010000
0!
02

#1015000
1!
12

#1016000
1&
1(
b110 )
16
18
b110 9
b1010 <
b1111 =
b1011 @
b1110 A

#1020000
0!
02

#1024000
0&
06

#1025000
1!
12
b1111 B

#1030000
0!
02

#1032000
1&
0(
16
08

#1033000
b1010 -
b1010 .
b1000 0
b111 1
b110 H

#1035000
1!
12
b1111 C
b10111 F

#1040000
0!
0&
02
06

#1045000
1!
12

#1048000
1&
1(
b111 )
16
18
b111 9
b1011 <
b1110 =
b1100 @
b1010 A

#1050000
0!
02

#1055000
1!
12
b1110 B

#1056000
0&
06

#1060000
0!
02

#1064000
1&
0(
16
08

#1065000
1!
b1011 -
b1011 .
b111 0
b1000 1
12
b1110 C
b10110 F
b111 H

#1070000
0!
02

#1072000
0&
06

#1075000
1!
12

#1080000
0!
1&
1(
b1000 )
02
16
18
b1000 9
b1100 <
b1010 =
b1101 @
b1011 A

#1085000
1!
12
b1010 B

#1088000
0&
06

#1090000
0!
02

#1095000
1!
12
b1010 C
b10010 F

#1096000
1&
0(
16
08

#1097000
b1100 -
b1100 .
b110 0
b1001 1
b1000 H

#1100000
0!
02

#1104000
0&
06

#1105000
1!
12

#1110000
0!
02

#1112000
1&
1(
b1001 )
16
18
b1001 9
b1101 <
b1011 =
b1110 @
b1001 A

#1115000
1!
12
b1011 B

#1120000
0!
0&
02
06

#1125000
1!
12
b1011 C
b10011 F

#1128000
1&
0(
16
08

#1129000
b1101 -
b1101 .
b101 0
b1010 1
b1001 H

#1130000
0!
02

#1135000
1!
12

#1136000
0&
06

#1140000
0!
02

#1144000
1&
1(
b1010 )
16
18
b1010 9
b1110 <
b1001 =
b1111 @
b1000 A

#1145000
1!
12
b1001 B

#1150000
0!
02

#1152000
0&
06

#1155000
1!
12
b1001 C
b10001 F

#1160000
0!
1&
0(
02
16
08

#1161000
b1110 -
b1110 .
b100 0
b1011 1
b1010 H

#1165000
1!
12

#1168000
0&
06

#1170000
0!
02

#1175000
1!
12

#1176000
1&
1(
b1011 )
16
18
b1011 9
b1111 <
b1000 =
b10000 @
b11000 A

#1180000
0!
02

#1184000
0&
06

#1185000
1!
12
b1000 B

#1190000
0!
02

#1192000
1&
0(
16
08

#1193000
b1111 -
b1111 .
b11 0
b1100 1
b1011 H

#1195000
1!
12
b1000 C
b10000 F

#1200000
0!
0&
02
06

#1205000
1!
12

#1208000
1&
1(
b1100 )
16
18
b1100 9
b10000 <
b11000 =
b10001 @
b11001 A

#1210000
0!
02

#1215000
1!
12
b11000 B

#1216000
0&
06

#1220000
0!
02

#1224000
1&
0(
16
08

#1225000
1!
b10000 -
b0 .
b10 0
b1101 1
12
b11000 C
b0 F
b1100 H

#1230000
0!
02

#1232000
0&
06

#1235000
1!
12

#1240000
0!
1&
1(
b1101 )
02
16
18
b1101 9
b10001 <
b11001 =
b10010 @
b11011 A

#1245000
1!
12
b11001 B

#1248000
0&
06

#1250000
0!
02

#1255000
1!
12
b11001 C
b1 F

#1256000
1&
0(
16
08

#1257000
b10001 -
b1 .
b1 0
b1110 1
b1101 H

#1260000
0!
02

#1264000
0&
06

#1265000
1!
12

#1270000
0!
02

#1272000
1&
1(
b1110 )
1*
16
18
b1110 9
b10010 <
b11011 =
b10011 @
b11010 A

#1275000
1!
12
b11011 B

#1280000
0!
0&
02
06

#1285000
1!
12
b11011 C
b11 F

#1288000
1&
0(
16
08

#1289000
b10010 -
b10 .
b0 0
b1111 1
b1110 H

#1290000
0!
02

#1295000
1!
12

#1296000
0&
06

#1300000
0!
02

#1304000
1&
b10000 1
16

#1305000
1!
12

#1310000
0!
02

#1312000
0&
06

#1315000
1!
12

